{
    "directions": [
        "Heat the broth, cumin, black pepper, onion and green pepper in a 3-quart saucepan over medium-high heat to a boil. Stir in the rice. Reduce the heat to low. Cover and cook for 20 minutes or until the rice is tender.",
        "Stir the beans in the saucepan and cook until the mixture is hot."
    ],
    "ingredients": [
        "1 3/4 cups Swanson\u00ae Chicken Broth (Regular, Natural Goodness\u00ae or Certified Organic)",
        "1/2 teaspoon ground cumin",
        "1/8 teaspoon ground black pepper",
        "1 medium onion, chopped",
        "1 small green pepper, chopped",
        "3/4 cup uncooked regular long-grain white rice",
        "1 (15 ounce) can kidney beans, rinsed and drained"
    ],
    "language": "en-US",
    "source": "allrecipes.com",
    "tags": [],
    "title": "Easy Seasoned Beans and Rice",
    "url": "http://allrecipes.com/recipe/220047/easy-seasoned-beans-and-rice/"
}
