{
    "directions": [
        "Cook 1/2 pound stemmed Fresno chiles (8\u201310) and 6 peeled garlic cloves in a large saucepan of boiling salted water until chiles turn bright red, about 2 minutes; drain. Blend chiles, garlic, and 3 tablespoons red wine vinegar in a blender until almost smooth; season with salt. Let cool."
    ],
    "ingredients": [
        "1/2 pound stemmed Fresno chiles",
        "6 peeled garlic cloves",
        "3 tablespoons red wine vinegar",
        "salt"
    ],
    "language": "en-US",
    "source": "www.epicurious.com",
    "tags": [
        "Condiment",
        "Vinegar",
        "Hot Pepper"
    ],
    "title": "Fresno Chile Hot Sauce",
    "url": "http://www.epicurious.com/recipes/food/views/fresno-chile-hot-sauce-51241880"
}
