{
    "directions": [
        "Preheat oven to 375 degrees F (190 degrees C). Grease 12 muffin cups.",
        "Mix almond milk, applesauce, apple, raisins, pecans, flax meal, eggs, brown sugar, cinnamon, and nutmeg together in a bowl; stir in oats until well mixed. Let sit for 5 minutes. Scoop mixture into the prepared muffin cups using an ice cream scoop.",
        "Bake in the preheated oven until lightly browned, about 20 minutes. Let oatmeal sit in muffin tin for 5 minutes before transferring to a wire rack to cool completely."
    ],
    "ingredients": [
        "1 1/2 cups almond milk",
        "1 cup applesauce",
        "1 apple, diced",
        "1/2 cup raisins",
        "1/2 cup pecans",
        "1/2 cup flax seed meal",
        "2 eggs",
        "1/4 cup brown sugar",
        "1 1/2 teaspoons ground cinnamon",
        "1 1/2 teaspoons ground nutmeg",
        "2 1/2 cups old-fashioned rolled oats"
    ],
    "language": "en-US",
    "source": "allrecipes.com",
    "tags": [],
    "title": "Healthy Apple Spice Baked Oatmeal",
    "url": "http://allrecipes.com/recipe/244223/healthy-apple-spice-baked-oatmeal/"
}
