{
    "directions": [
        "In a medium saucepan bring water to a boil. Add rice and stir. Reduce heat, cover and simmer for 20 minutes.",
        "Preheat oven to 350 degrees F (175 degrees C).",
        "In a large skillet over medium high heat, place the ground lamb, onion, garlic, thyme, basil and ground mustard. Cook until the lamb is evenly brown and the onion is soft. Stir the rice into the mixture.",
        "Stuff the acorn squash halves with the ground lamb mixture. Season with salt and pepper.",
        "Place stuffed squash on a medium baking sheet. Bake in the preheated oven 30 minutes, or until the squash is tender."
    ],
    "ingredients": [
        "3 cups water",
        "1 1/2 cups uncooked white rice",
        "1 pound ground lamb",
        "1 cup finely chopped onion",
        "1 clove garlic, minced",
        "1/2 teaspoon dried thyme",
        "1/2 teaspoon dried basil",
        "1 teaspoon ground mustard",
        "1 acorn squash, halved and seeded",
        "salt and pepper to taste"
    ],
    "language": "en-US",
    "source": "allrecipes.com",
    "tags": [],
    "title": "Lamb and Squash",
    "url": "http://allrecipes.com/recipe/24856/lamb-and-squash/"
}
