{
    "directions": [
        "Place 1 scoop of ice cream into each of two tall glasses. Pour root beer carefully over the ice cream. Add another scoop and repeat.  If possible, repeat again. Top each with whipped cream and cherries."
    ],
    "ingredients": [
        "1/2 pint vanilla ice cream",
        "1 (12 fluid ounce) can or bottle root beer",
        "1/2 cup whipped cream",
        "4 maraschino cherries"
    ],
    "language": "en-US",
    "source": "allrecipes.com",
    "tags": [],
    "title": "Gourmet Root Beer Float",
    "url": "http://allrecipes.com/recipe/20731/gourmet-root-beer-float/"
}
