{
    "directions": [
        "Line a baking sheet with waxed paper. Arrange Snack Factory(R) Pretzel Crisps(R) on sheet.",
        "Melt chocolate in a microwave-safe glass or ceramic bowl in 15-second intervals, stirring after each melting, 1 to 3 minutes.",
        "Dip each apricot in the dark chocolate, allowing excess to drip back into bowl. Place on top of Snack Factory(R) Pretzel Crisp(R).",
        "Sprinkle lightly with toasted pecans. Allow chocolate to set before serving."
    ],
    "ingredients": [
        "24 Original Snack Factory\u00ae Pretzel Crisps\u00ae",
        "6 ounces dark chocolate candy melts or baking chocolate",
        "24 dried apricot halves",
        "2 tablespoons chopped pecans, toasted"
    ],
    "language": "en-US",
    "source": "allrecipes.com",
    "tags": [],
    "title": "Dark Chocolate Covered Apricot Pretzel Crisps\u00ae",
    "url": "http://allrecipes.com/recipe/247417/dark-chocolate-covered-apricot-pretze/"
}
