{
    "directions": [
        "Measure the orange juice and vodka into a shaker and add a scoop of ice. Cover and shake until the outside is frosty. Strain into a glass and serve."
    ],
    "ingredients": [
        "6 fluid ounces orange juice",
        "2 1/2 fluid ounces vanilla flavored vodka",
        "ice cubes"
    ],
    "language": "en-US",
    "source": "allrecipes.com",
    "tags": [],
    "title": "Orange Cream Delight (Screwdriver)",
    "url": "http://allrecipes.com/recipe/60833/orange-cream-delight-screwdriver/"
}
