{
    "directions": [
        "Place ground beef and ground pork sausage in a large, deep skillet. Cook over medium high heat until evenly brown.",
        "In a medium saucepan over low heat, melt processed cheese food. Stir in diced tomatoes with green chile peppers while processed cheese food is melting.",
        "Drain ground beef and ground sausage. Mix into the processed cheese food mixture. Transfer to a medium dish and serve warm."
    ],
    "ingredients": [
        "1/2 pound ground beef",
        "1/2 pound ground pork sausage",
        "2 pounds processed cheese food, cubed",
        "1 (10 ounce) can diced tomatoes with green chile peppers, with liquid"
    ],
    "language": "en-US",
    "source": "allrecipes.com",
    "tags": [],
    "title": "Spicy Melted Cheese Dip",
    "url": "http://allrecipes.com/recipe/24628/spicy-melted-cheese-dip/"
}
