{
    "directions": [
        "Combine water and rice in heavy medium saucepan. Bring to simmer. Reduce heat to low. Cover and cook until rice is tender and liquid is absorbed, about 20 minutes. Uncover and cool.",
        "Position rack in center of oven; preheat to 350\u00b0F. Butter 6- to 8-cup souffl\u00e9 dish. Place in roasting pan. Whisk milk and next 6 ingredients in large bowl to blend. Stir in raisins and 1 1/2 cups cooked rice (reserve any remaining rice for another use). Pour into dish. Sprinkle nutmeg over. Add enough hot water to roasting pan to come halfway up sides of dish. Bake until pudding is set in center and brown around edges, about 1 hour 5 minutes.",
        "Remove dish from water. Cool pudding at least 15 minutes. Spoon into bowls and serve warm or at room temperature with whipped cream."
    ],
    "ingredients": [
        "1 cup water",
        "1/2 cup long-grain white rice",
        "1 1/2 cups whole milk",
        "1/2 cup pure maple syrup",
        "2 large eggs",
        "1 large egg yolk",
        "1 teaspoon vanilla extract",
        "1/2 teaspoon grated lemon peel",
        "1/8 teaspoon salt",
        "3/4 cup raisins",
        "1/4 teaspoon ground nutmeg",
        "Whipped cream"
    ],
    "language": "en-US",
    "source": "www.epicurious.com",
    "tags": [
        "Milk/Cream",
        "Citrus",
        "Rice",
        "Dessert",
        "Kid-Friendly",
        "Lemon",
        "Dried Fruit",
        "Raisin",
        "Fall",
        "Winter",
        "Potluck",
        "Maple Syrup"
    ],
    "title": "Maple-Lemon-Raisin Rice Pudding",
    "url": "http://www.epicurious.com/recipes/food/views/maple-lemon-raisin-rice-pudding-4952"
}
