{
    "directions": [
        "Whisk vanilla ice cream, milk, rum, coffee liqueur, and vodka in a large punch bowl until frothy and liquid; garnish with nutmeg. Ladle into punch mugs."
    ],
    "ingredients": [
        "1 gallon vanilla ice cream, softened",
        "1 gallon milk",
        "4 3/4 cups dark rum",
        "4 3/4 cups coffee-flavored liqueur (such as Kahlua\u00ae)",
        "4 3/4 cups vodka",
        "1 pinch ground nutmeg, or to taste (optional)"
    ],
    "language": "en-US",
    "source": "allrecipes.com",
    "tags": [],
    "title": "Moose Milk",
    "url": "http://allrecipes.com/recipe/230533/moose-milk/"
}
