{
    "directions": [
        "Fill an old-fashioned glass with 1 cup ice.",
        "Combine vodka, coffee liqueur, Irish cream, and heavy cream in a cocktail shaker. Add ice; cover and shake until chilled. Strain into the prepared old-fashioned glass."
    ],
    "ingredients": [
        "1 cup ice",
        "1 fluid ounce vodka",
        "1 fluid ounce coffee-flavored liqueur (such as Kahlua\u00ae)",
        "1 fluid ounce Irish cream liqueur",
        "1 fluid ounce heavy cream",
        "1 cup ice"
    ],
    "language": "en-US",
    "source": "allrecipes.com",
    "tags": [],
    "title": "Mudslide Cocktail",
    "url": "http://allrecipes.com/recipe/222891/mudslide-cocktail/"
}
