{
    "directions": [
        "Fill a cocktail shaker with ice and top with brandy, raspberry-flavored liqueur, and coffee-flavored liqueur; cover shaker and shake vigorously for 20 seconds. Add cream and gently shake for 5 seconds. Strain drink into a cocktail glass."
    ],
    "ingredients": [
        "ice cubes",
        "1 1/2 fluid ounces brandy",
        "1/2 fluid ounce raspberry-flavored liqueur (such as Chambord\u00ae)",
        "1/2 fluid ounce coffee-flavored liqueur (such as Kahlua\u00ae)",
        "1 fluid ounce heavy whipping cream"
    ],
    "language": "en-US",
    "source": "allrecipes.com",
    "tags": [],
    "title": "Raspberry Dream Cocktail",
    "url": "http://allrecipes.com/recipe/241823/raspberry-dream-cocktail/"
}
